{
  "latestVersion": "1.6.4",
  "downloadUrl": "", 
  "notes": "<b>v1.6.4 Update: Critical Fixes & Sync</b><br><br>🛠 <b>Foundry v12 Fix:</b> Fixed a critical crash where adding phone patterns or importing data would fail on V12. The system now correctly identifies input fields across both v12 and v13 versions.<br><br>⚠️ <b>Version Sync:</b> Internal version tracking has been synchronized. This update will automatically reset update flags once to ensure your module is correctly aligned with the official release track.",
  "critical": false,
  "announcement": {
    "id": "",
    "show": false,
    "title": "",
    "content": ""
  }
}
